<annotation>
	<folder>collectedimages</folder>
	<filename>q.03d1a655-7dae-11ec-9e8e-3c91803ac546.jpg</filename>
	<path>C:\Users\LENOVO\Desktop\MHSS\MINI PROJECT 1A\MAIN\RealTimeObjectDetection\Tensorflow\workspace\images\collectedimages\q.03d1a655-7dae-11ec-9e8e-3c91803ac546.jpg</path>
	<source>
		<database>Unknown</database>
	</source>
	<size>
		<width>640</width>
		<height>480</height>
		<depth>3</depth>
	</size>
	<segmented>0</segmented>
	<object>
		<name>q</name>
		<pose>Unspecified</pose>
		<truncated>0</truncated>
		<difficult>0</difficult>
		<bndbox>
			<xmin>408</xmin>
			<ymin>250</ymin>
			<xmax>547</xmax>
			<ymax>369</ymax>
		</bndbox>
	</object>
</annotation>
